demosh/__init__.py
demosh/builtins.py
demosh/command.py
demosh/demostate.py
demosh/main.py
demosh/shellstate.py
demosh-0.6.0.dist-info/entry_points.txt
demosh-0.6.0.dist-info/LICENSE
demosh-0.6.0.dist-info/WHEEL
demosh-0.6.0.dist-info/METADATA
demosh-0.6.0.dist-info/RECORD
