Metadata-Version: 2.1
Name: demosh
Version: 0.6.0
Summary: demosh is a Demo SHell: it reads shell scripts or Markdown files and
Author-email: Flynn <demosh@flynn.kodachi.com>
Requires-Python: >=3.10
Classifier: License :: OSI Approved :: Apache Software License
Project-URL: Documentation, https://github.com/BuoyantIO/demosh#readme
Project-URL: Home, https://github.com/BuoyantIO/demosh
Project-URL: Issues, https://github.com/BuoyantIO/demosh/issues
Project-URL: Source, https://github.com/BuoyantIO/demosh
